bemcp/__init__.py
bemcp/decorator.py
bemcp/main.py
bemcp/utils.py
bemcp-0.1.6.dist-info/METADATA
bemcp-0.1.6.dist-info/WHEEL
bemcp-0.1.6.dist-info/top_level.txt
bemcp-0.1.6.dist-info/RECORD
