Metadata-Version: 2.4
Name: bemcp
Version: 0.1.6
Summary: A MCP Manager for LLM
Requires-Python: >=3.13
Requires-Dist: mcp[cli]>=1.6.0
